aioh2/__init__.py
aioh2/exceptions.py
aioh2/helper.py
aioh2/protocol.py
aioh2-0.2.3.dist-info/AUTHORS.rst
aioh2-0.2.3.dist-info/LICENSE
aioh2-0.2.3.dist-info/METADATA
aioh2-0.2.3.dist-info/WHEEL
aioh2-0.2.3.dist-info/top_level.txt
aioh2-0.2.3.dist-info/RECORD
