Metadata-Version: 2.1
Name: aioh2
Version: 0.2.3
Summary: HTTP/2 implementation with hyper-h2 on Python 3 asyncio.
Home-page: https://github.com/decentfox/aioh2
Author: Fantix King
Author-email: fantix.king@gmail.com
License: BSD
Keywords: aioh2
Classifier: Development Status :: 2 - Pre-Alpha
Classifier: Intended Audience :: Developers
Classifier: License :: OSI Approved :: BSD License
Classifier: Natural Language :: English
Classifier: Programming Language :: Python :: 3.7
Classifier: Programming Language :: Python :: 3.8
Classifier: Programming Language :: Python :: 3.9
Classifier: Programming Language :: Python :: 3.10
License-File: LICENSE
License-File: AUTHORS.rst
Requires-Dist: h2 <4,>=3
Requires-Dist: priority ==1.3.0
